fcsy/__init__.py
fcsy/_typing.py
fcsy/buffer.py
fcsy/fcs.py
fcsy/preprocessing.py
fcsy-0.10.0.dist-info/AUTHORS.rst
fcsy-0.10.0.dist-info/LICENSE
fcsy-0.10.0.dist-info/METADATA
fcsy-0.10.0.dist-info/WHEEL
fcsy-0.10.0.dist-info/top_level.txt
fcsy-0.10.0.dist-info/RECORD
