Metadata-Version: 2.1
Name: fcsy
Version: 0.10.0
Summary: A package for processing FCS files
Home-page: https://github.com/nehcgnay/fcsy
Author: yc
Author-email: yang.chen@scilifelab.se
License: MIT license
Keywords: fcsy
Platform: UNKNOWN
Classifier: Development Status :: 2 - Pre-Alpha
Classifier: Intended Audience :: Developers
Classifier: License :: OSI Approved :: MIT License
Classifier: Natural Language :: English
Classifier: Programming Language :: Python :: 3
Classifier: Programming Language :: Python :: 3.6
Classifier: Programming Language :: Python :: 3.7
Classifier: Programming Language :: Python :: 3.8
Classifier: Programming Language :: Python :: 3.9
Classifier: Programming Language :: Python :: 3.10
License-File: LICENSE
License-File: AUTHORS.rst
Requires-Dist: numpy (>=1.10.0)
Requires-Dist: pandas (>=0.24.0)
Provides-Extra: s3
Requires-Dist: boto3 (>=1.10.0) ; extra == 's3'
